{
  "entities": [
    {
      "entity_name": "3.1工作环境",
      "entity_type": "SECTION_TITLE",
      "description": "As a subsection of '3电气特性', this section outlines the operational environmental conditions required for the SOM-TL3588 industrial core board, including temperature, humidity, and other relevant factors.",
      "source_ids": [
        223
      ]
    },
    {
      "entity_name": "工作环境",
      "entity_type": "TASK_OR_PROBLEM",
      "description": "Refers to the environmental conditions under which the SOM-TL3588 industrial core board is designed to operate, as detailed in section 3.1.",
      "source_ids": [
        223
      ]
    }
  ],
  "relations": [
    {
      "src_entity_name": "工作环境",
      "tgt_entity_name": "3.1工作环境",
      "relation_name": "",
      "weight": 10.0,
      "description": "The concept of '工作环境' is a primary topic of section 3.1.",
      "source_ids": [
        223
      ]
    }
  ],
  "node_idx": 223
}